wifi_qrcode_generator.py
wifi_qrcode_generator/__init__.py
wifi_qrcode_generator/__main__.py
wifi_qrcode_generator/__version__.py
wifi_qrcode_generator/generator.py
wifi_qrcode_generator/runner.py
wifi_qrcode_generator-1.0.1.dist-info/LICENSE
wifi_qrcode_generator-1.0.1.dist-info/METADATA
wifi_qrcode_generator-1.0.1.dist-info/WHEEL
wifi_qrcode_generator-1.0.1.dist-info/entry_points.txt
wifi_qrcode_generator-1.0.1.dist-info/top_level.txt
wifi_qrcode_generator-1.0.1.dist-info/RECORD
