Metadata-Version: 2.1
Name: wifi-qrcode-generator
Version: 1.0.1
Summary: Generate a QR code for your WiFi network to let others quickly connect.
Home-page: https://github.com/lakhanmankani/wifi_qrcode_generator
Author: Lakhan Mankani
Author-email: lakhan.mankani@gmail.com
License: MIT
Keywords: WiFi,qrcode
Classifier: Development Status :: 5 - Production/Stable
Classifier: Environment :: Console
Classifier: Intended Audience :: End Users/Desktop
Classifier: License :: OSI Approved :: MIT License
Classifier: Operating System :: OS Independent
Classifier: Topic :: Communications
Classifier: Programming Language :: Python :: 3 :: Only
Classifier: Programming Language :: Python :: 3
Classifier: Programming Language :: Python :: 3.8
Classifier: Programming Language :: Python :: 3.9
Classifier: Programming Language :: Python :: 3.10
Classifier: Programming Language :: Python :: 3.11
License-File: LICENSE
